{
  "PDAc": {
    "stock": 90,
    "minimo": 20,
    "estado": "OK"
  },
  "TSA50%": {
    "stock": 19,
    "minimo": 20,
    "estado": "REPOSICI?N"
  },
  "TSA100%": {
    "stock": 0,
    "minimo": 10,
    "estado": "REPOSICI?N"
  },
  "KING B": {
    "stock": 49,
    "minimo": 10,
    "estado": "OK"
  },
  "CC": {
    "stock": 29,
    "minimo": 10,
    "estado": "OK"
  },
  "AN": {
    "stock": 48,
    "minimo": 10,
    "estado": "OK"
  },
  "PDA": {
    "stock": 0,
    "minimo": 10,
    "estado": "REPOSICI?N"
  },
  "_actualizado": "2026-06-18T13:08:36.572Z"
}